nlp_gym/__init__.py
nlp_gym/util.py
nlp_gym/core_components/__init__.py
nlp_gym/core_components/embeddings.py
nlp_gym/core_components/matching.py
nlp_gym/core_components/sampler.py
nlp_gym/data_pools/__init__.py
nlp_gym/data_pools/base.py
nlp_gym/data_pools/custom_multi_label_pools.py
nlp_gym/data_pools/custom_question_answering_pools.py
nlp_gym/data_pools/custom_seq_tagging_pools.py
nlp_gym/data_pools/multi_label_pool.py
nlp_gym/data_pools/question_answering_pool.py
nlp_gym/data_pools/registry.py
nlp_gym/envs/__init__.py
nlp_gym/envs/common/__init__.py
nlp_gym/envs/common/action_space.py
nlp_gym/envs/common/base_env.py
nlp_gym/envs/common/observation.py
nlp_gym/envs/common/reward.py
nlp_gym/envs/multi_label/__init__.py
nlp_gym/envs/multi_label/env.py
nlp_gym/envs/multi_label/featurizer.py
nlp_gym/envs/multi_label/observation.py
nlp_gym/envs/multi_label/reward.py
nlp_gym/envs/question_answering/__init__.py
nlp_gym/envs/question_answering/env.py
nlp_gym/envs/question_answering/featurizer.py
nlp_gym/envs/question_answering/observation.py
nlp_gym/envs/question_answering/reward.py
nlp_gym/envs/seq_tagging/__init__.py
nlp_gym/envs/seq_tagging/env.py
nlp_gym/envs/seq_tagging/featurizer.py
nlp_gym/envs/seq_tagging/observation.py
nlp_gym/envs/seq_tagging/reward.py
nlp_gym/metrics/__init__.py
nlp_gym/metrics/multi_label.py
nlp_gym/metrics/question_answer.py
nlp_gym/metrics/registry.py
nlp_gym/metrics/seq_tag.py
tests/__init__.py
nlp_gym-0.1.0.dist-info/LICENSE
nlp_gym-0.1.0.dist-info/METADATA
nlp_gym-0.1.0.dist-info/WHEEL
nlp_gym-0.1.0.dist-info/top_level.txt
nlp_gym-0.1.0.dist-info/RECORD
